latex_generator/__init__.py
latex_generator/latex_generator.py
my_latex_generator-0.1.0.dist-info/METADATA
my_latex_generator-0.1.0.dist-info/WHEEL
my_latex_generator-0.1.0.dist-info/top_level.txt
my_latex_generator-0.1.0.dist-info/RECORD
