Metadata-Version: 2.1
Name: my_latex_generator
Version: 0.1.0
Summary: A small package to generate LaTeX
Author: Mikhail Borisov
Author-email: mishaborisov2013@gmail.com
Classifier: Programming Language :: Python :: 3
Classifier: License :: OSI Approved :: MIT License
Classifier: Operating System :: OS Independent
Requires-Python: >=3.6
